nulled_auth/__init__.py
nulled_auth/auth.py
nulled_auth/exceptions.py
nulled_auth/util.py
nulled_auth-1.7.5.dist-info/METADATA
nulled_auth-1.7.5.dist-info/WHEEL
nulled_auth-1.7.5.dist-info/top_level.txt
nulled_auth-1.7.5.dist-info/RECORD
