Metadata-Version: 2.1
Name: nulled-auth
Version: 1.7.5
Summary: nulled.to release authentication package for python
Author: 0x69
Author-email: nulled0x69@protonmail.com
License: UNKNOWN
Keywords: python,authentication,nulled,release
Platform: UNKNOWN
Classifier: Development Status :: 3 - Alpha
Classifier: Intended Audience :: Developers
Classifier: Programming Language :: Python :: 3
Classifier: Operating System :: Microsoft :: Windows :: Windows 10
Classifier: Operating System :: POSIX :: Linux
Classifier: Environment :: MacOS X
Requires-Python: >=3
Requires-Dist: requests
